README.rst
setup.py
PyGoogleDrive/__init__.py
PyGoogleDrive/pygoogledrive.py
PyGoogleDrive.egg-info/PKG-INFO
PyGoogleDrive.egg-info/SOURCES.txt
PyGoogleDrive.egg-info/dependency_links.txt
PyGoogleDrive.egg-info/requires.txt
PyGoogleDrive.egg-info/top_level.txt