Metadata-Version: 1.0
Name: PyGoogleDrive
Version: 1.0.1
Summary: Google Drive API made easy with PyGoogleDrive
Home-page: https://github.com/fahadkhan09/pygoogledrive
Author: Fahad Khan
Author-email: fahadkhan6302@gmail.com
License: GPLv3+
Keywords: python,google drive,api,PyGoogleDrive
Platform: UNKNOWN
